{
    "appKeys": {},
    "capabilities": [
        ""
    ],
    "companyName": "youlosepoints@gmail.com",
    "longName": "DestinyTimer",
    "projectType": "pebblejs",
    "resources": {
        "media": [
            {
                "file": "images/menu_icon.png",
                "menuIcon": true,
                "name": "IMAGE_MENU_ICON",
                "type": "png"
            },
            {
                "file": "images/logo_splash.png",
                "name": "IMAGE_LOGO_SPLASH",
                "type": "png"
            },
            {
                "file": "images/tile_splash.png",
                "name": "IMAGE_TILE_SPLASH",
                "type": "png"
            },
            {
                "file": "fonts/UbuntuMono-Regular.ttf",
                "name": "MONO_FONT_14",
                "type": "font"
            }
        ]
    },
    "shortName": "DestinyTimer",
    "uuid": "24569e94-f739-4e20-82b2-c58d571368be",
    "versionCode": 1,
    "versionLabel": "1.0",
    "watchapp": {
        "watchface": false
    }
}
